pyneevo/__init__.py
pyneevo/api.py
pyneevo/errors.py
pyneevo/tank/__init__.py
pyneevo-1.0.6.dist-info/LICENSE
pyneevo-1.0.6.dist-info/METADATA
pyneevo-1.0.6.dist-info/WHEEL
pyneevo-1.0.6.dist-info/top_level.txt
pyneevo-1.0.6.dist-info/RECORD
